adx_mcp_server/__init__.py
adx_mcp_server/main.py
adx_mcp_server/server.py
mseep_adx_mcp_server-1.1.1.dist-info/licenses/LICENSE
mseep_adx_mcp_server-1.1.1.dist-info/METADATA
mseep_adx_mcp_server-1.1.1.dist-info/WHEEL
mseep_adx_mcp_server-1.1.1.dist-info/entry_points.txt
mseep_adx_mcp_server-1.1.1.dist-info/top_level.txt
mseep_adx_mcp_server-1.1.1.dist-info/RECORD
